[
  {
    "_id": "67b26e630acc9fc1f97361cd",
    "cod_documento": 7611756,
    "deputy_external_id": 220573,
    "year": 2023,
    "month": 9,
    "expense_type": "DIVULGAÇÃO DA ATIVIDADE PARLAMENTAR.",
    "document_type": "Nota Fiscal",
    "cod_tipo_documento": 0,
    "data_documento": "2023-09-20 00:00:00 UTC",
    "num_documento": "11",
    "valor_documento": 70000.0,
    "url_documento": "https://www.camara.leg.br/cota-parlamentar/documentos/publ/3576/2023/7611756.pdf",
    "nome_fornecedor": "ORBE PRODUTORA & SERVIÇOS LTDA",
    "cnpj_cpf_fornecedor": "49494655000152",
    "valor_liquido": 70000.0,
    "valor_glosa": 0.0,
    "num_ressarcimento": "",
    "cod_lote": 1970066,
    "parcela": 0,
    "deputy_name": "Dorinaldo Malafaia",
    "deputy_party": "PDT"
  },
  {
    "_id": "67b2c0950acc9fc1f9743802",
    "cod_documento": 7628954,
    "deputy_external_id": 141485,
    "year": 2023,
    "month": 9,
    "expense_type": "DIVULGAÇÃO DA ATIVIDADE PARLAMENTAR.",
    "document_type": "Nota Fiscal Eletrônica",
    "cod_tipo_documento": 4,
    "data_documento": "2023-10-20 00:00:00 UTC",
    "num_documento": "49638460",
    "valor_documento": 67500.0,
    "url_documento": "http://www.camara.leg.br/cota-parlamentar/nota-fiscal-eletronica?ideDocumentoFiscal=7628954",
    "nome_fornecedor": "VEGA GRAF DIGITAL LTDA",
    "cnpj_cpf_fornecedor": "41197900000158",
    "valor_liquido": 67500.0,
    "valor_glosa": 0.0,
    "num_ressarcimento": "",
    "cod_lote": 1979935,
    "parcela": 0,
    "deputy_name": "Luiz Carlos Busato",
    "deputy_party": "UNIÃO"
  },
  {
    "_id": "67b2df0f0acc9fc1f974a848",
    "cod_documento": 7614234,
    "deputy_external_id": 204570,
    "year": 2023,
    "month": 9,
    "expense_type": "DIVULGAÇÃO DA ATIVIDADE PARLAMENTAR.",
    "document_type": "Nota Fiscal",
    "cod_tipo_documento": 0,
    "data_documento": "2023-09-26 00:00:00 UTC",
    "num_documento": "00000646",
    "valor_documento": 64000.0,
    "url_documento": "https://www.camara.leg.br/cota-parlamentar/documentos/publ/3398/2023/7614234.pdf",
    "nome_fornecedor": "GRÁFICA E EDITORA SHALOM LTDA.",
    "cnpj_cpf_fornecedor": "03924350000132",
    "valor_liquido": 64000.0,
    "valor_glosa": 0.0,
    "num_ressarcimento": "",
    "cod_lote": 1971382,
    "parcela": 0,
    "deputy_name": "Pastor Gil",
    "deputy_party": "PL"
  },
  {
    "_id": "67b181dc0acc9fc1f972c3ed",
    "cod_documento": 7616857,
    "deputy_external_id": 204515,
    "year": 2023,
    "month": 9,
    "expense_type": "DIVULGAÇÃO DA ATIVIDADE PARLAMENTAR.",
    "document_type": "Nota Fiscal",
    "cod_tipo_documento": 0,
    "data_documento": "2023-09-18 00:00:00 UTC",
    "num_documento": "20238",
    "valor_documento": 51400.0,
    "url_documento": "https://www.camara.leg.br/cota-parlamentar/documentos/publ/3257/2023/7616857.pdf",
    "nome_fornecedor": "WALDIRENE ARACY FERREIRA MARIOSA",
    "cnpj_cpf_fornecedor": "05399603000121",
    "valor_liquido": 51400.0,
    "valor_glosa": 0.0,
    "num_ressarcimento": "",
    "cod_lote": 1973198,
    "parcela": 0,
    "deputy_name": "André Janones",
    "deputy_party": "AVANTE"
  },
  {
    "_id": "67b287440acc9fc1f973c135",
    "cod_documento": 7611443,
    "deputy_external_id": 204419,
    "year": 2023,
    "month": 9,
    "expense_type": "DIVULGAÇÃO DA ATIVIDADE PARLAMENTAR.",
    "document_type": "Nota Fiscal",
    "cod_tipo_documento": 0,
    "data_documento": "2023-09-20 00:00:00 UTC",
    "num_documento": "350",
    "valor_documento": 39900.0,
    "url_documento": "https://www.camara.leg.br/cota-parlamentar/documentos/publ/3238/2023/7611443.pdf",
    "nome_fornecedor": "INVENT COMUNICACAO  E COMERCIO DE MATERIAS PARA COMUNICACAO VISUAL LTDA.",
    "cnpj_cpf_fornecedor": "45886612000161",
    "valor_liquido": 39900.0,
    "valor_glosa": 0.0,
    "num_ressarcimento": "",
    "cod_lote": 1969909,
    "parcela": 0,
    "deputy_name": "Glaustin da Fokus",
    "deputy_party": "PODE"
  },
  {
    "_id": "67b271270acc9fc1f9736d92",
    "cod_documento": 7620340,
    "deputy_external_id": 220674,
    "year": 2023,
    "month": 9,
    "expense_type": "DIVULGAÇÃO DA ATIVIDADE PARLAMENTAR.",
    "document_type": "Nota Fiscal",
    "cod_tipo_documento": 0,
    "data_documento": "2023-09-26 00:00:00 UTC",
    "num_documento": "00005105",
    "valor_documento": 39200.0,
    "url_documento": "https://www.camara.leg.br/cota-parlamentar/documentos/publ/3527/2023/7620340.pdf",
    "nome_fornecedor": "CALIGRAFIA LTDA",
    "cnpj_cpf_fornecedor": "83648246000100",
    "valor_liquido": 39200.0,
    "valor_glosa": 0.0,
    "num_ressarcimento": "",
    "cod_lote": 1975157,
    "parcela": 0,
    "deputy_name": "Dra. Alessandra Haber",
    "deputy_party": "MDB"
  },
  {
    "_id": "67b2638b0acc9fc1f9732fc9",
    "cod_documento": 7623384,
    "deputy_external_id": 220582,
    "year": 2023,
    "month": 9,
    "expense_type": "DIVULGAÇÃO DA ATIVIDADE PARLAMENTAR.",
    "document_type": "Nota Fiscal",
    "cod_tipo_documento": 0,
    "data_documento": "2023-10-09 00:00:00 UTC",
    "num_documento": "19",
    "valor_documento": 38000.0,
    "url_documento": "https://www.camara.leg.br/cota-parlamentar/documentos/publ/3627/2023/7623384.pdf",
    "nome_fornecedor": "FEAT WORK LTDA",
    "cnpj_cpf_fornecedor": "50061432000180",
    "valor_liquido": 38000.0,
    "valor_glosa": 0.0,
    "num_ressarcimento": "",
    "cod_lote": 1976989,
    "parcela": 0,
    "deputy_name": "Daniel Barbosa",
    "deputy_party": "PP"
  },
  {
    "_id": "67b284050acc9fc1f973b40f",
    "cod_documento": 7604452,
    "deputy_external_id": 74383,
    "year": 2023,
    "month": 9,
    "expense_type": "DIVULGAÇÃO DA ATIVIDADE PARLAMENTAR.",
    "document_type": "Nota Fiscal Eletrônica",
    "cod_tipo_documento": 4,
    "data_documento": "2023-09-06 00:00:00 UTC",
    "num_documento": "10316",
    "valor_documento": 38000.0,
    "url_documento": "http://www.camara.leg.br/cota-parlamentar/nota-fiscal-eletronica?ideDocumentoFiscal=7604452",
    "nome_fornecedor": "GALZON EDITORA GRAFICA LTDA",
    "cnpj_cpf_fornecedor": "07436265000186",
    "valor_liquido": 38000.0,
    "valor_glosa": 0.0,
    "num_ressarcimento": "",
    "cod_lote": 1966216,
    "parcela": 0,
    "deputy_name": "Giacobo",
    "deputy_party": "PL"
  },
  {
    "_id": "67b2db640acc9fc1f9749b09",
    "cod_documento": 7603590,
    "deputy_external_id": 178987,
    "year": 2023,
    "month": 9,
    "expense_type": "DIVULGAÇÃO DA ATIVIDADE PARLAMENTAR.",
    "document_type": "Nota Fiscal",
    "cod_tipo_documento": 0,
    "data_documento": "2023-09-05 00:00:00 UTC",
    "num_documento": "00027272",
    "valor_documento": 37990.0,
    "url_documento": "https://www.camara.leg.br/cota-parlamentar/documentos/publ/2957/2023/7603590.pdf",
    "nome_fornecedor": "ATIVAONLINE SERVIÇOS LTDA",
    "cnpj_cpf_fornecedor": "04241587000181",
    "valor_liquido": 37990.0,
    "valor_glosa": 0.0,
    "num_ressarcimento": "",
    "cod_lote": 1965696,
    "parcela": 0,
    "deputy_name": "Orlando Silva",
    "deputy_party": "PCdoB"
  },
  {
    "_id": "67b17e5d0acc9fc1f972b233",
    "cod_documento": 7601086,
    "deputy_external_id": 74057,
    "year": 2023,
    "month": 9,
    "expense_type": "DIVULGAÇÃO DA ATIVIDADE PARLAMENTAR.",
    "document_type": "Nota Fiscal Eletrônica",
    "cod_tipo_documento": 4,
    "data_documento": "2023-09-01 00:00:00 UTC",
    "num_documento": "59",
    "valor_documento": 35940.0,
    "url_documento": "http://www.camara.leg.br/cota-parlamentar/nota-fiscal-eletronica?ideDocumentoFiscal=7601086",
    "nome_fornecedor": "ON - Z IMPRESSAO, DIVULGACAO & MARKETING DIGITAL LTDA",
    "cnpj_cpf_fornecedor": "49870873000144",
    "valor_liquido": 35940.0,
    "valor_glosa": 0.0,
    "num_ressarcimento": "",
    "cod_lote": 1964296,
    "parcela": 0,
    "deputy_name": "Alice Portugal",
    "deputy_party": "PCdoB"
  }
]